vtoollib/__init__.py
vtoollib/add.py
vtoollib/imPlug.py
vtoollib/image.py
vtoollib/logger.py
vtoollib/data/__init__.py
vtoollib/data/data.txt
vtoollib/font/NotoSansCJK-Bold.ttc
vtoollib/font/__init__.py
vtoollib/lib/__init__.py
vtoollib/lib/imPlug.cp310-win_amd64.pyd
vtoollib/lib/image.cp310-win_amd64.pyd
vtoollib/lib/logger.cp310-win_amd64.pyd
vtoollib-0.0.5.dist-info/METADATA
vtoollib-0.0.5.dist-info/WHEEL
vtoollib-0.0.5.dist-info/licenses/LICENSE
vtoollib-0.0.5.dist-info/RECORD
