Metadata-Version: 2.1
Name: vtoollib
Version: 0.0.5
Summary: vtool is a package for fast iterating deep learning experiment, it has some helpful tricks which are often used in competition and work by me, and more tricks are on the way!
Author-email: ljj <junjielv123@163.com>
License: Copyright (c) 2018 The Python Packaging Authority
License-File: LICENSE
Classifier: License :: OSI Approved :: MIT License
Classifier: Operating System :: OS Independent
Classifier: Programming Language :: Python :: 3
Requires-Python: ==3.10
